smilepngquant/Error.py
smilepngquant/PNGQuant.py
smilepngquant/__init__.py
test/__init__.py
smilepngquant-1.1.0.dist-info/LICENSE.txt
smilepngquant-1.1.0.dist-info/METADATA
smilepngquant-1.1.0.dist-info/WHEEL
smilepngquant-1.1.0.dist-info/top_level.txt
smilepngquant-1.1.0.dist-info/RECORD
