Metadata-Version: 2.1
Name: smilepngquant
Version: 1.1.0
Summary: That is a bridge of pngquant for python3
Home-page: https://github.com/sitthykun/smilepngquant
Author: Sitthykun LY
Author-email: ly.sitthykun@gmail.com
Project-URL: Bug Tracker, https://github.com/sitthykun/smilepngquant/issues
Classifier: Programming Language :: Python :: 3.5
Classifier: Programming Language :: Python :: 3.6
Classifier: Programming Language :: Python :: 3.7
Classifier: Programming Language :: Python :: 3.8
Classifier: Programming Language :: Python :: 3.9
Classifier: Programming Language :: Python :: 3.10
Classifier: License :: OSI Approved :: MIT License
Classifier: Operating System :: OS Independent
Requires-Python: >=3.5
License-File: LICENSE.txt
